readme_builder/__init__.py
readme_builder/cli.py
readme_builder-0.1.3.dist-info/LICENSE
readme_builder-0.1.3.dist-info/METADATA
readme_builder-0.1.3.dist-info/WHEEL
readme_builder-0.1.3.dist-info/entry_points.txt
readme_builder-0.1.3.dist-info/RECORD
