Metadata-Version: 2.1
Name: readme-builder
Version: 0.1.3
Summary: Create contextual README.md files
Author: Akshita Dixit
Author-email: akshitadixit.int@gmail.com
Requires-Python: >=3.9,<4.0
Classifier: Programming Language :: Python :: 3
Classifier: Programming Language :: Python :: 3.9
Classifier: Programming Language :: Python :: 3.10
Classifier: Programming Language :: Python :: 3.11
Classifier: Programming Language :: Python :: 3.12
Requires-Dist: requests (==2.32.3)
